healthkit_to_sqlite/__init__.py
healthkit_to_sqlite/cli.py
healthkit_to_sqlite/utils.py
healthkit_to_sqlite-1.0.1.dist-info/LICENSE
healthkit_to_sqlite-1.0.1.dist-info/METADATA
healthkit_to_sqlite-1.0.1.dist-info/WHEEL
healthkit_to_sqlite-1.0.1.dist-info/entry_points.txt
healthkit_to_sqlite-1.0.1.dist-info/top_level.txt
healthkit_to_sqlite-1.0.1.dist-info/RECORD
