Metadata-Version: 2.1
Name: healthkit-to-sqlite
Version: 1.0.1
Summary: Convert an Apple Healthkit export zip to a SQLite database
Home-page: https://datasette.io/tools/healthkit-to-sqlite
Author: Simon Willison
License: Apache License, Version 2.0
Project-URL: Issues, https://github.com/dogsheep/healthkit-to-sqlite/issues
Project-URL: CI, https://github.com/dogsheep/healthkit-to-sqlite/actions
Project-URL: Changelog, https://github.com/dogsheep/healthkit-to-sqlite/releases
Platform: UNKNOWN
Requires-Dist: sqlite-utils (>=2.4.4)
Provides-Extra: test
Requires-Dist: pytest ; extra == 'test'
